ShishangZuiquanShejimoshiDaoxue/README.md
ShishangZuiquanShejimoshiDaoxue/__init__.py
ShishangZuiquanShejimoshiDaoxue/__main__.py
ShishangZuiquanShejimoshiDaoxue/file.epub
ShishangZuiquanShejimoshiDaoxue/index.html
ShishangZuiquanShejimoshiDaoxue/css/__init__.py
ShishangZuiquanShejimoshiDaoxue/css/annotations.css
ShishangZuiquanShejimoshiDaoxue/css/main.css
ShishangZuiquanShejimoshiDaoxue/css/normalize.css
ShishangZuiquanShejimoshiDaoxue/css/popup.css
ShishangZuiquanShejimoshiDaoxue/font/__init__.py
ShishangZuiquanShejimoshiDaoxue/font/fontello.eot
ShishangZuiquanShejimoshiDaoxue/font/fontello.svg
ShishangZuiquanShejimoshiDaoxue/font/fontello.ttf
ShishangZuiquanShejimoshiDaoxue/font/fontello.woff
ShishangZuiquanShejimoshiDaoxue/img/__init__.py
ShishangZuiquanShejimoshiDaoxue/img/annotator-glyph-sprite.png
ShishangZuiquanShejimoshiDaoxue/img/annotator-icon-sprite.png
ShishangZuiquanShejimoshiDaoxue/img/apple-touch-icon.png
ShishangZuiquanShejimoshiDaoxue/img/cancelfullscreen.png
ShishangZuiquanShejimoshiDaoxue/img/close.png
ShishangZuiquanShejimoshiDaoxue/img/fullscreen.png
ShishangZuiquanShejimoshiDaoxue/img/loader.gif
ShishangZuiquanShejimoshiDaoxue/img/menu-icon.png
ShishangZuiquanShejimoshiDaoxue/img/save.png
ShishangZuiquanShejimoshiDaoxue/img/saved.png
ShishangZuiquanShejimoshiDaoxue/img/settings-s.png
ShishangZuiquanShejimoshiDaoxue/img/settings.png
ShishangZuiquanShejimoshiDaoxue/img/star.png
ShishangZuiquanShejimoshiDaoxue/js/__init__.py
ShishangZuiquanShejimoshiDaoxue/js/epub.js
ShishangZuiquanShejimoshiDaoxue/js/epub.min.js
ShishangZuiquanShejimoshiDaoxue/js/epub.min.map
ShishangZuiquanShejimoshiDaoxue/js/hooks.min.js
ShishangZuiquanShejimoshiDaoxue/js/hooks.min.map
ShishangZuiquanShejimoshiDaoxue/js/reader.js
ShishangZuiquanShejimoshiDaoxue/js/reader.js.map
ShishangZuiquanShejimoshiDaoxue/js/reader.min.js
ShishangZuiquanShejimoshiDaoxue/js/reader.min.map
ShishangZuiquanShejimoshiDaoxue/js/hooks/__init__.py
shishang_zuiquan_shejimoshi_daoxue-2024.3.1.0.dist-info/METADATA
shishang_zuiquan_shejimoshi_daoxue-2024.3.1.0.dist-info/WHEEL
shishang_zuiquan_shejimoshi_daoxue-2024.3.1.0.dist-info/entry_points.txt
shishang_zuiquan_shejimoshi_daoxue-2024.3.1.0.dist-info/top_level.txt
shishang_zuiquan_shejimoshi_daoxue-2024.3.1.0.dist-info/RECORD
